lumo/__init__.py
lumo/cli.py
lumo/modules/__init__.py
lumo/modules/ai_assistant.py
lumo/modules/ai_notifications.py
lumo/modules/config.py
lumo/modules/game_mode.py
lumo/modules/monitoring.py
lumo/modules/performance.py
lumo/modules/plugins.py
lumo/modules/security.py
lumo/modules/ui.py
lumo/utils/__init__.py
lumo/utils/logging.py
lumo/utils/platform.py
huxly-2.0.0.dist-info/METADATA
huxly-2.0.0.dist-info/WHEEL
huxly-2.0.0.dist-info/entry_points.txt
huxly-2.0.0.dist-info/top_level.txt
huxly-2.0.0.dist-info/RECORD
