Metadata-Version: 2.4
Name: huxly
Version: 2.0.0
Summary: Huxly 2.0 - Professional PC utility with AI notifications
Author-email: "Tyora Inc." <support@tyora.io>
Maintainer-email: "Tyora Inc." <support@tyora.io>
License: Proprietary
Project-URL: Homepage, https://tyora.io
Project-URL: Repository, https://github.com/tyora/huxly
Project-URL: Documentation, https://docs.tyora.io/huxly
Project-URL: Issues, https://github.com/tyora/huxly/issues
Keywords: pc-utility,optimization,gaming,performance,security,ai,notifications
Classifier: Development Status :: 4 - Beta
Classifier: Environment :: Console
Classifier: Intended Audience :: End Users/Desktop
Classifier: Operating System :: OS Independent
Classifier: Programming Language :: Python :: 3.8
Classifier: Programming Language :: Python :: 3.9
Classifier: Programming Language :: Python :: 3.10
Classifier: Programming Language :: Python :: 3.11
Classifier: Programming Language :: Python :: 3.12
Classifier: Programming Language :: Python :: 3.13
Classifier: Topic :: System :: Systems Administration
Classifier: Topic :: Utilities
Requires-Python: >=3.8
Requires-Dist: click>=8.0
Requires-Dist: psutil>=5.9
Requires-Dist: rich>=12.0
Requires-Dist: requests>=2.25
Requires-Dist: pytest>=7.0
